{
    "ogbn_arxiv": {
      "task_level": "node",
      "num_hops": 2,
      "sampling": true,
      "neighbor_size": 15,
      "random_seed": 42
    },
    "wikics": {
      "task_level": "node",
      "num_hops": 2,
      "sampling": true,
      "neighbor_size": 15,
      "random_seed": 42
    },
    "aminer": {
      "task_level": "node",
      "num_hops": 2,
      "sampling": true,
      "neighbor_size": 15,
      "random_seed": 42
    },
    "twitch": {
      "task_level": "node",
      "num_hops": 2,
      "sampling": true,
      "neighbor_size": [15, 5],
      "random_seed": 42
    },
    "ogbl_vessel": {
      "task_level": "edge",
      "num_hops": 2,
      "sampling": true,
      "neighbor_size": [15, 5],
      "random_seed": 42
    },
    "movielens1m": {
      "task_level": "edge",
      "num_hops": 1,
      "sampling": true,
      "neighbor_size": [50],
      "random_seed": 42
    },
    "yelp_review": {
      "task_level": "edge",
      "num_hops": 1,
      "sampling": true,
      "neighbor_size": [50],
      "random_seed": 42
    },
    "fingerprint": {
      "task_level": "graph"
    },
    "bace": {
      "task_level": "graph"
    },
    "esol": {
      "task_level": "graph"
    },
    "chebi20": {
      "task_level": "graph"
    }
}